sccli/Emitter.py
sccli/Parser.py
sccli/Socketcluster.py
sccli/__init__.py
sktclcli_minbin-0.1.4.dist-info/LICENSE.txt
sktclcli_minbin-0.1.4.dist-info/METADATA
sktclcli_minbin-0.1.4.dist-info/WHEEL
sktclcli_minbin-0.1.4.dist-info/top_level.txt
sktclcli_minbin-0.1.4.dist-info/RECORD
